beangrow/__init__.py
beangrow/compute_returns.py
beangrow/compute_returns_beam.py
beangrow/config.py
beangrow/config_pb2.py
beangrow/configure.py
beangrow/download_prices.py
beangrow/download_prices_from_file.py
beangrow/investments.py
beangrow/reports.py
beangrow/returns.py
beangrow-1.0.1.dist-info/METADATA
beangrow-1.0.1.dist-info/WHEEL
beangrow-1.0.1.dist-info/entry_points.txt
beangrow-1.0.1.dist-info/top_level.txt
beangrow-1.0.1.dist-info/RECORD
