Metadata-Version: 2.2
Name: beangrow
Version: 1.0.1
Summary: Returns calculations on portfolios in Beancount Resources
Author-email: Martin Blais <blais@furius.ca>
Maintainer-email: Martin Blais <blais@furius.ca>
Keywords: accounting,ledger,beancount,returns,investments
Classifier: License :: OSI Approved :: GNU General Public License v2 (GPLv2)
Classifier: Programming Language :: Python :: 3 :: Only
Classifier: Programming Language :: Python :: 3.10
Classifier: Programming Language :: Python :: 3.11
Classifier: Programming Language :: Python :: 3.12
Classifier: Programming Language :: Python :: 3.13
Classifier: Programming Language :: SQL
Classifier: Topic :: Office/Business :: Financial :: Accounting
Requires-Python: >=3.10
Requires-Dist: numpy>=1.26.4
Requires-Dist: pandas>=2.2.2
Requires-Dist: matplotlib>=3.9.0
Requires-Dist: beancount>=2.3.6
Requires-Dist: scipy>=1.13.1
Requires-Dist: beanprice>=1.2.1
Requires-Dist: pandas-stubs>=2.2.2.240514
Requires-Dist: matplotlib-stubs>=0.2.0
Requires-Dist: protobuf>=5.29.3
